{
    "IMAGEM": "https://heycar.com.br/images/2018/Agosto/208-19.jpg",
    "NOME": "208-active-pack-1.2-2019",
    "ANO": "2019",
    "MARCA": "peugeot",
    "MODELO": "208",
    "ESPECIFICACAO": {
        "Marca:": "Peugeot",
        "Modelo:": "208",
        "Versão:": "Active Pack 1.2 2019",
        "Combustível:": "Flex - Etanol e/ou Gasolina",
        "Origem:": "Nacional",
        "Categoria:": "Hatch",
        "Portas:": "4",
        "Ocupantes:": "5",
        "Geração:": "1",
        "Garantia:": "3 anos"
    },
    "MOTOR": {
        "Instalação:": "Dianteiro",
        "Posição:": "Transversal",
        "Aspiração:": "Natural",
        "Alimentação:": "Injeção eletrônica multiponto",
        "Cilindrada:": "1.199 cc",
        "Cilindros:": "3, em linha",
        "Válvulas por cilindro:": "4",
        "Comando de válvulas:": "Duplo, no cabeçote, correia dentada",
        "Variação do comando:": "Ciclo de admissão e escape",
        "Potência máxima (cv):": "90 (E) / 84 (G) @ 5.750 rpm",
        "Torque máximo (kgfm):": "13 (E) / 12,2 (G) @ 2.750 rpm",
        "Potência específica:": "75,1 cv/litro",
        "Torque específico:": "10,8 kgfm/litro",
        "Taxa de compressão:": "12,5:1",
        "Rel. peso/potência:": "11,7 kg/cv",
        "Rel. peso/torque:": "81 kg/kgfm",
        "Curso dos pistões:": "90,5 mm",
        "Diâmetro dos cilindros:": "75 mm",
        "Tuchos:": "Mecânicos",
        "Código do motor:": "EB2FF"
    },
    "TRANSMISSÃO": {
        "Câmbio:": "Manual",
        "Marchas:": "5",
        "Acoplamento:": "Embreagem monodisco a seco",
        "Tração:": "Dianteira",
        "Código do câmbio:": "MA/5"
    },
    "DESEMPENHO": {
        "Acel. 0 a 100 km/h:": "12,8 seg",
        "Velocidade máxima:": "177 km/h"
    },
    "CONSUMO": {
        "Cidade em km/l:": "9,6 (E) / 13,9 (G)",
        "Estrada em km/l:": "10,7 (E) / 15,5 (G)",
        "Autonomia em km:": "589 (E) / 853 (G)"
    },
    "SUSPENSÃO": {
        "Dianteira:": "Independente, McPherson",
        "Traseira:": "Eixo de torção",
        "Elemento elástico:": "Mola helicoidal"
    },
    "FREIOS": {
        "Dianteira:": "Disco sólido",
        "Traseira:": "Tambor"
    },
    "DIREÇÃO": {
        "Assistência:": "Elétrica",
        "Diâmetro de giro:": "11,2 m"
    },
    "PNEUS": {
        "Dianteira:": "195/60 R15",
        "Traseira:": "195/60 R15",
        "Altura do flanco:": "117 mm"
    },
    "AERODINÂMICA": {
        "Área frontal:": "2,11 m²",
        "Coef. aerodinâmico:": "0,33 Cx"
    },
    "DIMENSÕES": {
        "Comprimento:": "3.975 mm",
        "Altura:": "1.472 mm",
        "Largura:": "1.702 mm",
        "Entre-eixos:": "2.541 mm",
        "Bitola dianteira:": "1.475 mm",
        "Bitola traseira:": "1.470 mm",
        "Vão livre do solo:": "informação não disponível"
    },
    "PESO E CAPACIDADES": {
        "Peso:": "1.053 kg",
        "Porta-malas:": "285 litros",
        "Carga útil:": "400 kg",
        "Tanque combustível:": "55 litros"
    }
}