{
    "IMAGEM": "https://heycar.com.br/images/2022/setembro/mercedes-benz-glb-200.jpg",
    "NOME": "glb-200-launch-edition-1.3-turbo-2020",
    "ANO": "2020",
    "MARCA": "mercedes-benz",
    "MODELO": "glb",
    "ESPECIFICACAO": {
        "Marca:": "Mercedes-Benz",
        "Modelo:": "GLB 200",
        "Versão:": "Launch Edition 1.3 Turbo 2020",
        "Combustível:": "Gasolina",
        "Origem:": "Importado",
        "Categoria:": "SUV",
        "Portas:": "4",
        "Ocupantes:": "7",
        "Geração:": "1",
        "Garantia:": "2 anos"
    },
    "MOTOR": {
        "Instalação:": "Dianteiro",
        "Posição:": "Transversal",
        "Aspiração:": "Turbocompressor",
        "Alimentação:": "Injeção direta de combustível",
        "Cilindrada:": "1.332 cc",
        "Cilindros:": "4, em linha",
        "Válvulas por cilindro:": "4",
        "Comando de válvulas:": "Duplo, no cabeçote, corrente",
        "Variação do comando:": "Admissão e escape",
        "Potência máxima em CV:": "163 @ 5.500 rpm",
        "Torque máximo em kgfm:": "25,5 @ 1.620 rpm",
        "Potência específica:": "122,4 cv/litro",
        "Torque específico:": "19,1 kgfm/litro",
        "Taxa de compressão:": "10,6:1",
        "Relação peso/potência:": "10 kg/cv",
        "Relação peso/torque:": "63,9 kg/kgfm",
        "Curso dos pistões:": "81,4 mm",
        "Diâmetro dos cilindros:": "72,2 mm",
        "Tuchos:": "Hidráulicos",
        "Código do motor:": "M282DE14"
    },
    "TRANSMISSÃO": {
        "Câmbio:": "Automatizado",
        "Marchas:": "7",
        "Acoplamento:": "Embreagem dupla banhada a óleo",
        "Tração:": "Dianteira",
        "Código do câmbio:": "7G-DCT"
    },
    "DESEMPENHO": {
        "Acel. 0 a 100 km/h:": "9,1 seg",
        "Velocidade máxima:": "207 km/h"
    },
    "CONSUMO": {
        "Cidade em km/l:": "10,1",
        "Estrada em km/l:": "11,7",
        "Autonomia em km:": "608"
    },
    "SUSPENSÃO": {
        "Dianteira:": "Independente, McPherson",
        "Traseira:": "Independente, multibraço",
        "Elemento elástico:": "Mola helicoidal"
    },
    "FREIOS": {
        "Dianteira:": "Disco ventilado",
        "Traseira:": "Disco sólido"
    },
    "DIREÇÃO": {
        "Assistência:": "Elétrica",
        "Diâmetro de giro:": "11,7 m"
    },
    "PNEUS": {
        "Dianteira:": "235/50 R19",
        "Traseira:": "235/50 R19",
        "Estepe:": "Kit de reparo e enchimento"
    },
    "AERODINÂMICA": {
        "Área frontal:": "2,59 m²",
        "Coef. aerodinâmico:": "0,30 Cx"
    },
    "DIMENSÕES": {
        "Comprimento:": "4.634 mm",
        "Altura:": "1.659 mm",
        "Largura:": "1.834 mm",
        "Entre eixos:": "2.829 mm",
        "Bitola dianteira:": "1.605 mm",
        "Bitola traseira:": "1.606 mm",
        "Vão livre do solo:": "135 mm"
    },
    "PESO E CAPACIDADES": {
        "Peso:": "1.630 kg",
        "Porta-malas:": "500 litros (5 lug) / 130 litros (7 lug)",
        "Carga útil:": "não disponível",
        "Tanque combustível:": "52 litros"
    }
}