{
    "IMAGEM": "https://heycar.com.br/images/2021/Marco/Volvo-S40-04.jpg",
    "NOME": "s40-2.4-2006",
    "ANO": "2006",
    "MARCA": "volvo",
    "MODELO": "s40",
    "ESPECIFICACAO": {
        "Marca:": "Volvo",
        "Modelo:": "S40",
        "Versão:": "2.4 2006",
        "Combustível:": "Gasolina",
        "Origem:": "Importado",
        "Categoria:": "Sedã",
        "Portas:": "4",
        "Ocupantes:": "5",
        "Geração:": "2",
        "Garantia:": "1 ano"
    },
    "MOTOR": {
        "Instalação:": "Dianteiro",
        "Posição:": "Transversal",
        "Aspiração:": "Natural",
        "Alimentação:": "Injeção eletrônica multiponto",
        "Cilindrada:": "2.435 cc",
        "Cilindros:": "5, em linha",
        "Válvulas por cilindro:": "4",
        "Comando de válvulas:": "Duplo, no cabeçote, correia dentada",
        "Variação do comando:": "não variável",
        "Potência máxima (cv):": "170 @ 6.000 rpm",
        "Torque máximo (kgfm):": "23,4 @ 4.400 rpm",
        "Potência específica:": "69,4 cv/litro",
        "Torque específico:": "9,6 kgfm/litro",
        "Taxa de compressão:": "10,3:1",
        "Rel. peso/potência:": "8,1 kg/cv",
        "Rel. peso/torque:": "58,5 kg/kgfm",
        "Curso dos pistões:": "90 mm",
        "Diâmetro dos cilindros:": "83 mm",
        "Tuchos:": "informação não disponível",
        "Código do motor:": "B5244S"
    },
    "TRANSMISSÃO": {
        "Câmbio:": "Automático",
        "Marchas:": "5",
        "Acoplamento:": "Conversor de torque",
        "Tração:": "Dianteira",
        "Código do câmbio:": "Aisin AW55-50"
    },
    "DESEMPENHO": {
        "Acel. 0 a 100 km/h:": "8,9 seg",
        "Velocidade máxima:": "215 km/h"
    },
    "CONSUMO": {
        "Cidade em km/l:": "7,5",
        "Estrada em km/l:": "12",
        "Autonomia em km:": "744"
    },
    "SUSPENSÃO": {
        "Dianteira:": "Independente, McPherson",
        "Traseira:": "Independente, multibraço",
        "Elemento elástico:": "Mola helicoidal"
    },
    "FREIOS": {
        "Dianteira:": "Disco ventilado",
        "Traseira:": "Disco sólido"
    },
    "DIREÇÃO": {
        "Assistência:": "Hidráulica",
        "Diâmetro de giro:": "10,6 m"
    },
    "PNEUS": {
        "Dianteira:": "195/50 R16",
        "Traseira:": "195/50 R16",
        "Altura do flanco:": "98 mm"
    },
    "AERODINÂMICA": {
        "Área frontal:": "2,18 m²",
        "Coef. aerodinâmico:": "0,31 Cx"
    },
    "DIMENSÕES": {
        "Comprimento:": "4.468 mm",
        "Altura:": "1.452 mm",
        "Largura:": "1.770 mm",
        "Entre eixos:": "2.640 mm",
        "Bitola dianteira:": "1.535 mm",
        "Bitola traseira:": "1.531 mm",
        "Vão livre do solo:": "informação não disponível"
    },
    "PESO E CAPACIDADES": {
        "Peso:": "1.369 kg",
        "Porta-malas:": "405 litros",
        "Carga útil:": "404 kg",
        "Tanque combustível:": "62 litros"
    }
}