{
    "IMAGEM": "https://heycar.com.br/images/2019/Maio/Blazer_96.jpg",
    "NOME": "std-2.2-1996",
    "ANO": "1996",
    "MARCA": "chevrolet",
    "MODELO": "std",
    "ESPECIFICACAO": {
        "Marca:": "Chevrolet",
        "Modelo:": "Blazer",
        "Versão:": "STD 2.2",
        "Combustível:": "Gasolina",
        "Origem:": "Nacional",
        "Categoria:": "SUV",
        "Porte:": "Médio",
        "Portas:": "4",
        "Ocupantes:": "5",
        "Geração:": "1",
        "Garantia:": "1 ano"
    },
    "MOTOR": {
        "Instalação:": "Dianteiro",
        "Posição:": "Longitudinal",
        "Aspiração:": "Natural",
        "Alimentação:": "Injeção eletrônica multiponto",
        "Cilindrada:": "2.198 cc",
        "Cilindros:": "4, em linha",
        "Válvulas por cilindro:": "2",
        "Comando de válvulas:": "Único, no cabeçote",
        "Acionamento:": "Correia dentada",
        "Variação do comando:": "não variável",
        "Potência máx. (CV):": "106 @ 4.800 rpm",
        "Torque máx. (kgfm):": "19,2 @ 2.500 rpm",
        "Potência específica:": "48,2 cv/litro",
        "Torque específico:": "8,7 kgfm/litro",
        "Taxa de compressão:": "9,2:1",
        "Rel. peso/potência:": "15,3 kg/cv",
        "Rel. peso/torque:": "84,4 kg/kgfm",
        "Curso dos pistões:": "94,6 mm",
        "Diâmetro dos cilindros:": "86 mm",
        "Tuchos:": "Hidráulicos",
        "Código do motor:": "GM Família II"
    },
    "TRANSMISSÃO": {
        "Câmbio:": "Manual",
        "Marchas:": "5",
        "Acoplamento:": "Embreagem monodisco a seco",
        "Tração:": "Traseira",
        "Código do câmbio:": "informação não disponível"
    },
    "DESEMPENHO": {
        "Acel. 0 a 100 km/h:": "18,2 seg",
        "Velocidade máxima:": "150 km/h"
    },
    "CONSUMO": {
        "Cidade em km/l:": "6,8",
        "Estrada em km/l:": "9,5",
        "Autonomia em km:": "722"
    },
    "SUSPENSÃO": {
        "Dianteira:": "Independente, braços sobrepostos",
        "Traseira:": "Eixo rígido",
        "Elemento elástico:": "Mola parabólica de lâmina única"
    },
    "FREIOS": {
        "Dianteira:": "Disco ventilado",
        "Traseira:": "Tambor"
    },
    "DIREÇÃO": {
        "Assistência:": "Hidráulica",
        "Diâmetro de giro:": "12,2 m"
    },
    "PNEUS": {
        "Dianteira:": "205/75 R15",
        "Traseira:": "205/75 R15",
        "Altura do flanco:": "154 mm",
        "Estepe:": "informação não disponível"
    },
    "AERODINÂMICA": {
        "Área frontal:": "informação não disponível",
        "Coef. aerodinâmico:": "informação não disponível"
    },
    "DIMENSÕES": {
        "Comprimento:": "4.608 mm",
        "Altura:": "1.596 mm",
        "Largura:": "1.731 mm",
        "Entre eixos:": "2.718 mm",
        "Bitola dianteira:": "1.454 mm",
        "Bitola traseira:": "1.399 mm",
        "Vão livre do solo:": "228 mm"
    },
    "PESO E CAPACIDADES": {
        "Peso:": "1.620 kg",
        "Porta-malas:": "456 litros",
        "Carga útil:": "700 kg",
        "Tanque combustível:": "76 litros"
    }
}