{
    "IMAGEM": "https://heycar.com.br/images/2017/Janeiro/Galerias/Volks/Jetta.jpg",
    "NOME": "jetta-highline-2.0-tsi-dsg",
    "ANO": "DSG",
    "MARCA": "volkswagen",
    "MODELO": "jetta",
    "ESPECIFICACAO": {
        "Marca:": "Volkswagen",
        "Modelo:": "Jetta",
        "Versão:": "Highline 2.0 TSi DSG",
        "Ano/modelo:": "2017",
        "Detalhes:": "Importado, sedan, 4 portas, 3 anos de garantia"
    },
    "MOTOR": {
        "Instalação:": "Dianteiro",
        "Posição:": "Transversal",
        "Aspiração:": "Turbo",
        "Cilindrada:": "1.984 cc",
        "Cilindros:": "4, em linha",
        "Comando de válvulas:": "No cabeçote, corrente, variável",
        "Válvulas por cilindro:": "4",
        "Combustível:": "Gasolina",
        "Potência:": "211 cv @ 5.000 rpm",
        "Torque:": "28,6 kgfm @ 1.500 rpm",
        "Taxa de compressão:": "9,61"
    },
    "TRANSMISSÃO": {
        "Câmbio:": "Automatizado",
        "Marchas:": "6",
        "Tração:": "Dianteira"
    },
    "DESEMPENHO": {
        "Acel. 0 a 100 km/h:": "7,2 s",
        "Velocidade máxima:": "241 km/h"
    },
    "CONSUMO": {
        "Urbano:": "9,4 km/l",
        "Rodoviário:": "12,5 km/l",
        "Autonomia:": "687 km"
    },
    "SUSPENSÃO": {
        "Dianteira:": "Independente, McPherson",
        "Traseira:": "Independente, multibraço"
    },
    "DIREÇÃO": {
        "Assistência:": "Elétrica",
        "Diâmetro de giro:": "11,1 m"
    },
    "FREIOS": {
        "Dianteiros:": "Discos ventilados",
        "Traseiros:": "Discos"
    },
    "PNEUS": {
        "Dianteiros:": "225/45 R17",
        "Traseiros:": "225/45 R17"
    },
    "DIMENSÕES": {
        "Comprimento:": "4.659 mm",
        "Altura:": "1.473 mm",
        "Largura:": "1.778 mm",
        "Entre-eixos:": "2.651 mm",
        "Vão livre do solo:": "não informado"
    },
    "PESO E CAPACIDADES": {
        "Peso:": "1.376 kg",
        "Porta-malas:": "510 litros",
        "Carga útil:": "562 kg",
        "Tanque combustível:": "55 litros"
    }
}