{
    "IMAGEM": "https://heycar.com.br/images/2021/Marco/Volkswagen-Parati-89.jpg",
    "NOME": "parati-cl-1.6-1996",
    "ANO": "1996",
    "MARCA": "volkswagen",
    "MODELO": "parati",
    "ESPECIFICACAO": {
        "Marca:": "Volkswagen",
        "Modelo:": "Parati",
        "Versão:": "CL 1.6",
        "Origem:": "Nacional",
        "Detalhes:": "Perua, 2 portas, 5 ocupantes"
    },
    "MOTOR": {
        "Instalação:": "Dianteiro",
        "Posição:": "Longitudinal",
        "Aspiração:": "Natural",
        "Alimentação:": "Carburador",
        "Cilindrada:": "1.596 cc",
        "Cilindros:": "4, em linha",
        "Comando de válvulas:": "No cabeçote, correia dentada",
        "Válvulas por cilindro:": "2",
        "Combustível:": "Gasolina",
        "Potência em CV:": "80 @ 5.600 rpm",
        "Torque em kgfm:": "12,7 @ 2.600 rpm",
        "Taxa de compressão:": "8,5:1",
        "Código do motor:": "AP-1600"
    },
    "TRANSMISSÃO": {
        "Câmbio:": "Manual",
        "Marchas:": "5",
        "Acoplamento:": "Embreagem monodisco a seco",
        "Tração:": "Dianteira",
        "Código do câmbio:": "não disponível"
    },
    "DESEMPENHO": {
        "Acel. 0 a 100 km/h:": "11,9 s",
        "Velocidade máxima:": "160 km/h"
    },
    "CONSUMO": {
        "Cidade em km/l:": "11,5",
        "Estrada em km/l:": "14,5",
        "Autonomia em km:": "682"
    },
    "SUSPENSÃO": {
        "Dianteira:": "Independente, McPherson",
        "Traseira:": "Eixo de torção",
        "Elemento elástico:": "Mola helicoidal"
    },
    "FREIOS": {
        "Dianteira:": "Disco",
        "Traseira:": "Tambor"
    },
    "DIREÇÃO": {
        "Assistência:": "Sem assistência",
        "Diâmetro de giro:": "10,2 m"
    },
    "PNEUS": {
        "Dianteira:": "155/80/R13",
        "Traseira:": "155/80/R13"
    },
    "AERODINÂMICA": {
        "Área frontal:": "1,90 m²",
        "Coef. aerodinâmico:": "0,41 CX"
    },
    "DIMENSÕES": {
        "Comprimento:": "4.075 mm",
        "Altura:": "1.368 mm",
        "Largura:": "1.622 mm",
        "Entre eixos:": "2.358 mm",
        "Bitola dianteira:": "1.350 mm",
        "Bitola traseira:": "1.370 mm",
        "Vão livre do solo:": "130 mm"
    },
    "PESO E CAPACIDADES": {
        "Peso:": "940 kg",
        "Porta-malas:": "530 litros",
        "Carga útil:": "450 kg",
        "Tanque combustível:": "47 litros"
    }
}