{
    "IMAGEM": "https://heycar.com.br/images/2021/Junho/Ford-Bronco-2021.jpg",
    "NOME": "bronco-sport-wildtrak-2.0-turbo-2021",
    "ANO": "2021",
    "MARCA": "ford",
    "MODELO": "bronco",
    "ESPECIFICACAO": {
        "Marca:": "Ford",
        "Modelo:": "Bronco Sport",
        "Versão:": "Wildtrak 2.0 Turbo 2021",
        "Combustível:": "Gasolina",
        "Origem:": "Importado",
        "Categoria:": "SUV",
        "Portas:": "4",
        "Ocupantes:": "5",
        "Geração:": "1",
        "Garantia:": "3 anos"
    },
    "MOTOR": {
        "Instalação:": "Dianteiro",
        "Posição:": "Transversal",
        "Aspiração:": "Turbocompressor",
        "Alimentação:": "Injeção direta de combustível",
        "Cilindrada:": "1.999 cc",
        "Cilindros:": "4, em linha",
        "Válvulas por cilindro:": "4",
        "Comando de válvulas:": "Duplo, no cabeçote, corrente",
        "Variação do comando:": "Admissão e escape",
        "Potência máxima em CV:": "248 @ 5.500 rpm",
        "Torque máximo em kgfm:": "38 @ 3.000 rpm",
        "Potência específica:": "124,1 cv/litro",
        "Torque específico:": "19 kgfm/litro",
        "Taxa de compressão:": "10:1",
        "Relação peso/potência:": "6,8 kg/cv",
        "Relação peso/torque:": "44,2 kg/kgfm",
        "Curso dos pistões:": "83,1 mm",
        "Diâmetro dos cilindros:": "87,5 mm",
        "Tuchos:": "Hidráulicos",
        "Código do motor:": "EcoBoost"
    },
    "TRANSMISSÃO": {
        "Câmbio:": "Automático CVT",
        "Marchas:": "8",
        "Acoplamento:": "Conversor de torque",
        "Tração:": "Integral sob demanda",
        "Código do câmbio:": "8F"
    },
    "DESEMPENHO": {
        "Acel. 0 a 100 km/h:": "8 seg",
        "Velocidade máxima:": "180 km/h"
    },
    "CONSUMO": {
        "Cidade em km/l:": "6",
        "Estrada em km/l:": "10",
        "Autonomia em km:": "600"
    },
    "SUSPENSÃO": {
        "Dianteira:": "Independente, McPherson",
        "Traseira:": "Independente, multibraço",
        "Elemento elástico:": "Molas helicoidais"
    },
    "FREIOS": {
        "Dianteira:": "Disco ventilado",
        "Traseira:": "Disco sólido"
    },
    "DIREÇÃO": {
        "Assistência:": "Elétrica",
        "Diâmetro de giro:": "11,4 m"
    },
    "PNEUS": {
        "Dianteira:": "225/65 R17",
        "Traseira:": "225/65 R17",
        "Estepe:": "225/65 R17"
    },
    "AERODINÂMICA": {
        "Área frontal:": "não disponível",
        "Coef. aerodinâmico:": "não disponível"
    },
    "DIMENSÕES": {
        "Comprimento:": "4.386 mm",
        "Altura:": "1.813 mm",
        "Largura:": "1.888 mm",
        "Entre eixos:": "2.670 mm",
        "Bitola dianteira:": "1.610 mm",
        "Bitola traseira:": "1.595 mm",
        "Vão livre do solo:": "223 mm"
    },
    "PESO E CAPACIDADES": {
        "Peso:": "1.681 kg",
        "Porta-malas:": "482 litros",
        "Carga útil:": "600 kg",
        "Tanque combustível:": "60 litros"
    }
}