{
    "IMAGEM": "https://heycar.com.br/images/2020/Novembro/AX.jpg",
    "NOME": "ax-gti-1.4-1993",
    "ANO": "1993",
    "MARCA": "citroen",
    "MODELO": "ax",
    "ESPECIFICACAO": {
        "Marca:": "Citroën",
        "Modelo:": "Ax",
        "Versão:": "GTi 1.4 1993",
        "Propulsão:": "Combustão interna",
        "Combustível:": "Gasolina",
        "Origem:": "Importado",
        "Categoria:": "Hatch",
        "Porte:": "Compacto",
        "Portas:": "2",
        "Ocupantes:": "5",
        "Geração:": "1",
        "Garantia:": "1 ano"
    },
    "MOTOR": {
        "Instalação:": "Dianteiro",
        "Posição:": "Transversal",
        "Aspiração:": "Natural",
        "Alimentação:": "Injeção eletrônica multiponto",
        "Cilindrada:": "1.361 cc",
        "Cilindros:": "4, em linha",
        "Válvulas por cilindro:": "2",
        "Comando de válvulas:": "Único, no cabeçote",
        "Acionamento:": "Correia dentada",
        "Variação do comando:": "não variável",
        "Potência máxima CV:": "100 @ 6.800 rpm",
        "Torque máximo kgfm:": "12,5 @ 4.200 rpm",
        "Potência específica:": "73,5 cv/litro",
        "Torque específico:": "9,2 kgfm/litro",
        "Taxa de compressão:": "9,9:1",
        "Rel. peso/potência:": "8 kg/cv",
        "Rel. peso/torque:": "63,6 kg/kgfm",
        "Curso dos pistões:": "77 mm",
        "Diâmetro cilindros:": "75 mm",
        "Tuchos:": "Hidráulicos",
        "Código do motor:": "TU3FJ2"
    },
    "TRANSMISSÃO": {
        "Câmbio:": "Manual",
        "Marchas:": "5",
        "Acoplamento:": "Embreagem monodisco a seco",
        "Tração:": "Dianteira",
        "Código do câmbio:": "BE3/5"
    },
    "DESEMPENHO": {
        "Acel. 0 a 100 km/h:": "9,4 seg",
        "Velocidade máxima:": "190 km/h"
    },
    "CONSUMO": {
        "Cidade em km/l:": "10,9",
        "Estrada em km/l:": "12,9",
        "Autonomia em km:": "555"
    },
    "SUSPENSÃO": {
        "Dianteira:": "Independente, McPherson",
        "Traseira:": "Independente, braço arrastado",
        "Elemento elástico:": "Mola helicoidal"
    },
    "FREIOS": {
        "Dianteira:": "Disco ventilado",
        "Traseira:": "Disco sólido"
    },
    "DIREÇÃO": {
        "Assistência:": "não assistida",
        "Diâmetro de giro:": "10,6 m"
    },
    "PNEUS": {
        "Dianteira:": "185/60 R13",
        "Traseira:": "185/60 R13",
        "Altura do flanco:": "111 mm",
        "Estepe:": "informação não disponível"
    },
    "AERODINÂMICA": {
        "Área frontal:": "1,82 m²",
        "Coef. aerodinâmico:": "0,31 Cx"
    },
    "DIMENSÕES": {
        "Comprimento:": "3.517 mm",
        "Altura:": "1.340 mm",
        "Largura:": "1.596 mm",
        "Entre-eixos:": "2.280 mm",
        "Bitola dianteira:": "1.390 mm",
        "Bitola traseira:": "1.331 mm",
        "Vão livre do solo:": "informação não disponível"
    },
    "PESO E CAPACIDADES": {
        "Peso:": "795 kg",
        "Porta-malas:": "273 litros",
        "Carga útil:": "440 kg",
        "Tanque combustível:": "43 litros"
    }
}